papersurfer/__init__.py
papersurfer/_version.txt
papersurfer/bibtex.py
papersurfer/config.py
papersurfer/doi.py
papersurfer/dtos.py
papersurfer/exceptions.py
papersurfer/mattermost.py
papersurfer/papersurfer.py
papersurfer/ui_elements.py
papersurfer-0.13.0.dist-info/LICENSE
papersurfer-0.13.0.dist-info/METADATA
papersurfer-0.13.0.dist-info/WHEEL
papersurfer-0.13.0.dist-info/entry_points.txt
papersurfer-0.13.0.dist-info/top_level.txt
papersurfer-0.13.0.dist-info/RECORD
