Metadata-Version: 2.1
Name: papersurfer
Version: 0.13.0
Summary: UNKNOWN
Home-page: UNKNOWN
Author: Johann Jacobsohn
Author-email: johann.jacobsohn@uni-hamburg.de
License: MIT
Platform: UNKNOWN
Classifier: License :: OSI Approved :: MIT License
Classifier: Programming Language :: Python :: 3
Classifier: Programming Language :: Python :: 3.7
Classifier: Development Status :: 1 - Planning
Requires-Dist: requests
Requires-Dist: mattermostdriver
Requires-Dist: urwid
Requires-Dist: configargparse
Requires-Dist: tinydb
Requires-Dist: dataclasses
Requires-Dist: xdgappdirs
Provides-Extra: dev
Requires-Dist: flake8 ; extra == 'dev'
Requires-Dist: pylint (==2.4.4) ; extra == 'dev'
Requires-Dist: pycodestyle ; extra == 'dev'
Requires-Dist: pydocstyle ; extra == 'dev'
Requires-Dist: twine ; extra == 'dev'
Requires-Dist: pytest ; extra == 'dev'
Requires-Dist: pytest-cov ; extra == 'dev'
Requires-Dist: pytest-datadir ; extra == 'dev'
